sqlalchemy_views/__init__.py
sqlalchemy_views/metadata.py
sqlalchemy_views/views.py
sqlalchemy_views-0.3.2.dist-info/LICENSE
sqlalchemy_views-0.3.2.dist-info/METADATA
sqlalchemy_views-0.3.2.dist-info/WHEEL
sqlalchemy_views-0.3.2.dist-info/top_level.txt
sqlalchemy_views-0.3.2.dist-info/RECORD
