Metadata-Version: 2.1
Name: sqlalchemy-views
Version: 0.3.2
Summary: Adds CreateView and DropView constructs to SQLAlchemy
Home-page: https://github.com/jklukas/sqlalchemy-views
Author: Jeff Klukas
Author-email: jeff@klukas.net
Maintainer: Jeff Klukas
Maintainer-email: jeff@klukas.net
Classifier: Development Status :: 4 - Beta
Classifier: Environment :: Console
Classifier: Intended Audience :: Developers
Classifier: License :: OSI Approved :: MIT License
Classifier: Natural Language :: English
Classifier: Operating System :: OS Independent
Classifier: Programming Language :: Python :: 2.6
Classifier: Programming Language :: Python :: 2.7
Classifier: Programming Language :: Python :: 3.6
Classifier: Programming Language :: Python :: 3.7
Classifier: Programming Language :: Python :: 3.8
Classifier: Programming Language :: Python :: 3.9
Classifier: Programming Language :: Python :: Implementation :: PyPy
Classifier: Programming Language :: SQL
Classifier: Topic :: Database
Classifier: Topic :: Database :: Database Engines/Servers
Classifier: Topic :: Software Development :: Libraries :: Python Modules
License-File: LICENSE
